{"provider_arguments":[],"resources":{"instance":{"arguments":[{"word":"name","kind":"String(R)","info":"Name of the instance"},{"word":"plan","kind":"String(R)","info":"Name of the plan"},{"word":"region","kind":"String(R)","info":"Name of the region you want to create your instance in"}],"attributes":[{"word":"apikey","kind":"String","info":"API key for the CloudMQTT instance"},{"word":"name","kind":"String","info":"Name of the instance"},{"word":"plan","kind":"String","info":"Name of the plan"},{"word":"region","kind":"String","info":"Name of the region you want to create your instance in"},{"word":"url","kind":"String","info":"URL of the CloudMQTT instance"},{"word":"id","kind":"String"}]}},"datas":{},"unknowns":{}}