{"provider_arguments":[],"resources":{"cached_image":{"arguments":[{"word":"aliases","kind":"List(O)"},{"word":"copy_aliases","kind":"Bool(O)"},{"word":"remote","kind":"String(O)"},{"word":"source_image","kind":"String(R)"},{"word":"source_remote","kind":"String(R)"}],"attributes":[{"word":"aliases","kind":"List"},{"word":"architecture","kind":"String"},{"word":"copied_aliases","kind":"List"},{"word":"copy_aliases","kind":"Bool"},{"word":"created_at","kind":"Int"},{"word":"fingerprint","kind":"String"},{"word":"remote","kind":"String"},{"word":"source_image","kind":"String"},{"word":"source_remote","kind":"String"},{"word":"id","kind":"String"}]},"container":{"arguments":[{"word":"config","kind":"Map(O)"},{"word":"device","kind":"List(O)(B)","subblock":[{"word":"name","kind":"String(R)"},{"word":"properties","kind":"Map(R)"},{"word":"type","kind":"String(R)"}]},{"word":"ephemeral","kind":"Bool(O)"},{"word":"file","kind":"List(O)(B)","subblock":[{"word":"content","kind":"String(O)"},{"word":"create_directories","kind":"Bool(O)"},{"word":"gid","kind":"Int(O)"},{"word":"mode","kind":"String(O)"},{"word":"source","kind":"String(O)"},{"word":"target_file","kind":"String(R)"},{"word":"uid","kind":"Int(O)"}]},{"word":"image","kind":"String(R)"},{"word":"limits","kind":"Map(O)"},{"word":"name","kind":"String(R)"},{"word":"privileged","kind":"Bool(O)"},{"word":"profiles","kind":"List(O)"},{"word":"remote","kind":"String(O)"}],"attributes":[{"word":"config","kind":"Map"},{"word":"device","kind":"List(B)","subblock":[{"word":"name","kind":"String"},{"word":"properties","kind":"Map"},{"word":"type","kind":"String"},{"word":"id","kind":"String"}]},{"word":"ephemeral","kind":"Bool"},{"word":"file","kind":"List(B)","subblock":[{"word":"content","kind":"String"},{"word":"create_directories","kind":"Bool"},{"word":"gid","kind":"Int"},{"word":"mode","kind":"String"},{"word":"source","kind":"String"},{"word":"target_file","kind":"String"},{"word":"uid","kind":"Int"},{"word":"id","kind":"String"}]},{"word":"image","kind":"String"},{"word":"ip_address","kind":"String"},{"word":"limits","kind":"Map"},{"word":"mac_address","kind":"String"},{"word":"name","kind":"String"},{"word":"privileged","kind":"Bool"},{"word":"profiles","kind":"List"},{"word":"remote","kind":"String"},{"word":"status","kind":"String"},{"word":"id","kind":"String"}]},"container_file":{"arguments":[{"word":"container_name","kind":"String(R)"},{"word":"content","kind":"String(O)"},{"word":"create_directories","kind":"Bool(O)"},{"word":"gid","kind":"Int(O)"},{"word":"mode","kind":"String(O)"},{"word":"remote","kind":"String(O)"},{"word":"source","kind":"String(O)"},{"word":"target_file","kind":"String(R)"},{"word":"uid","kind":"Int(O)"}],"attributes":[{"word":"container_name","kind":"String"},{"word":"content","kind":"String"},{"word":"create_directories","kind":"Bool"},{"word":"gid","kind":"Int"},{"word":"mode","kind":"String"},{"word":"remote","kind":"String"},{"word":"source","kind":"String"},{"word":"target_file","kind":"String"},{"word":"uid","kind":"Int"},{"word":"id","kind":"String"}]},"network":{"arguments":[{"word":"config","kind":"Map(R)"},{"word":"description","kind":"String(O)"},{"word":"name","kind":"String(R)"},{"word":"remote","kind":"String(O)"}],"attributes":[{"word":"config","kind":"Map"},{"word":"description","kind":"String"},{"word":"managed","kind":"Bool"},{"word":"name","kind":"String"},{"word":"remote","kind":"String"},{"word":"type","kind":"String"},{"word":"id","kind":"String"}]},"profile":{"arguments":[{"word":"config","kind":"Map(O)"},{"word":"description","kind":"String(O)"},{"word":"device","kind":"List(O)(B)","subblock":[{"word":"name","kind":"String(R)"},{"word":"properties","kind":"Map(R)"},{"word":"type","kind":"String(R)"}]},{"word":"name","kind":"String(R)"},{"word":"remote","kind":"String(O)"}],"attributes":[{"word":"config","kind":"Map"},{"word":"description","kind":"String"},{"word":"device","kind":"List(B)","subblock":[{"word":"name","kind":"String"},{"word":"properties","kind":"Map"},{"word":"type","kind":"String"},{"word":"id","kind":"String"}]},{"word":"name","kind":"String"},{"word":"remote","kind":"String"},{"word":"id","kind":"String"}]},"snapshot":{"arguments":[{"word":"container_name","kind":"String(R)"},{"word":"name","kind":"String(R)"},{"word":"remote","kind":"String(O)"},{"word":"stateful","kind":"Bool(O)"}],"attributes":[{"word":"container_name","kind":"String"},{"word":"creation_date","kind":"String"},{"word":"name","kind":"String"},{"word":"remote","kind":"String"},{"word":"stateful","kind":"Bool"},{"word":"id","kind":"String"}]},"storage_pool":{"arguments":[{"word":"config","kind":"Map(R)"},{"word":"driver","kind":"String(R)"},{"word":"name","kind":"String(R)"},{"word":"remote","kind":"String(O)"}],"attributes":[{"word":"config","kind":"Map"},{"word":"driver","kind":"String"},{"word":"name","kind":"String"},{"word":"remote","kind":"String"},{"word":"id","kind":"String"}]},"volume":{"arguments":[{"word":"config","kind":"Map(O)"},{"word":"name","kind":"String(R)"},{"word":"pool","kind":"String(R)"},{"word":"remote","kind":"String(O)"},{"word":"type","kind":"String(O)"}],"attributes":[{"word":"config","kind":"Map"},{"word":"expanded_config","kind":"Map"},{"word":"name","kind":"String"},{"word":"pool","kind":"String"},{"word":"remote","kind":"String"},{"word":"type","kind":"String"},{"word":"id","kind":"String"}]},"volume_container_attach":{"arguments":[{"word":"container_name","kind":"String(R)"},{"word":"device_name","kind":"String(O)"},{"word":"path","kind":"String(R)"},{"word":"pool","kind":"String(R)"},{"word":"remote","kind":"String(O)"},{"word":"volume_name","kind":"String(R)"}],"attributes":[{"word":"container_name","kind":"String"},{"word":"device_name","kind":"String"},{"word":"path","kind":"String"},{"word":"pool","kind":"String"},{"word":"remote","kind":"String"},{"word":"volume_name","kind":"String"},{"word":"id","kind":"String"}]}},"datas":{},"unknowns":{}}