{"provider_arguments":[],"resources":{"alert":{"arguments":[{"word":"active","kind":"Bool(O)"},{"word":"attributes","kind":"List(O)(B)","subblock":[{"word":"runbook_url","kind":"String(O)"}]},{"word":"condition","kind":"Set(O)(B)","subblock":[{"word":"detect_reset","kind":"Bool(O)"},{"word":"duration","kind":"Int(O)"},{"word":"metric_name","kind":"String(R)"},{"word":"source","kind":"String(O)"},{"word":"summary_function","kind":"String(O)"},{"word":"threshold","kind":"Float(O)"},{"word":"type","kind":"String(R)"}]},{"word":"description","kind":"String(O)"},{"word":"name","kind":"String(R)"},{"word":"rearm_seconds","kind":"Int(O)"},{"word":"services","kind":"Set(O)"}],"attributes":[{"word":"active","kind":"Bool"},{"word":"attributes","kind":"List(B)","subblock":[{"word":"runbook_url","kind":"String"},{"word":"id","kind":"String"}]},{"word":"condition","kind":"Set(B)","subblock":[{"word":"detect_reset","kind":"Bool"},{"word":"duration","kind":"Int"},{"word":"metric_name","kind":"String"},{"word":"source","kind":"String"},{"word":"summary_function","kind":"String"},{"word":"threshold","kind":"Float"},{"word":"type","kind":"String"},{"word":"id","kind":"String"}]},{"word":"description","kind":"String"},{"word":"name","kind":"String"},{"word":"rearm_seconds","kind":"Int"},{"word":"services","kind":"Set"},{"word":"id","kind":"String"}]},"metric":{"arguments":[{"word":"attributes","kind":"List(O)(B)","subblock":[{"word":"aggregate","kind":"Bool(O)"},{"word":"color","kind":"String(O)"},{"word":"display_max","kind":"String(O)"},{"word":"display_min","kind":"String(O)"},{"word":"display_stacked","kind":"Bool(O)"},{"word":"display_units_long","kind":"String(O)"},{"word":"display_units_short","kind":"String(O)"},{"word":"gap_detection","kind":"Bool(O)"}]},{"word":"composite","kind":"String(O)"},{"word":"description","kind":"String(O)"},{"word":"display_name","kind":"String(O)"},{"word":"name","kind":"String(R)"},{"word":"period","kind":"Int(O)"},{"word":"type","kind":"String(R)"}],"attributes":[{"word":"attributes","kind":"List(B)","subblock":[{"word":"aggregate","kind":"Bool"},{"word":"color","kind":"String"},{"word":"created_by_ua","kind":"String"},{"word":"display_max","kind":"String"},{"word":"display_min","kind":"String"},{"word":"display_stacked","kind":"Bool"},{"word":"display_units_long","kind":"String"},{"word":"display_units_short","kind":"String"},{"word":"gap_detection","kind":"Bool"},{"word":"id","kind":"String"}]},{"word":"composite","kind":"String"},{"word":"description","kind":"String"},{"word":"display_name","kind":"String"},{"word":"name","kind":"String"},{"word":"period","kind":"Int"},{"word":"type","kind":"String"},{"word":"id","kind":"String"}]},"service":{"arguments":[{"word":"settings","kind":"String(R)"},{"word":"title","kind":"String(R)"},{"word":"type","kind":"String(R)"}],"attributes":[{"word":"id","kind":"Int"},{"word":"settings","kind":"String"},{"word":"title","kind":"String"},{"word":"type","kind":"String"},{"word":"id","kind":"String"}]},"space":{"arguments":[{"word":"name","kind":"String(R)"}],"attributes":[{"word":"id","kind":"Int"},{"word":"name","kind":"String"},{"word":"id","kind":"String"}]},"space_chart":{"arguments":[{"word":"label","kind":"String(O)"},{"word":"max","kind":"Float(O)"},{"word":"min","kind":"Float(O)"},{"word":"name","kind":"String(R)"},{"word":"related_space","kind":"Int(O)"},{"word":"space_id","kind":"Int(R)"},{"word":"stream","kind":"Set(O)(B)","subblock":[{"word":"color","kind":"String(O)"},{"word":"composite","kind":"String(O)"},{"word":"group_function","kind":"String(O)"},{"word":"max","kind":"Float(O)"},{"word":"metric","kind":"String(O)"},{"word":"min","kind":"Float(O)"},{"word":"name","kind":"String(O)"},{"word":"period","kind":"Int(O)"},{"word":"source","kind":"String(O)"},{"word":"summary_function","kind":"String(O)"},{"word":"transform_function","kind":"String(O)"},{"word":"units_long","kind":"String(O)"},{"word":"units_short","kind":"String(O)"}]},{"word":"type","kind":"String(R)"}],"attributes":[{"word":"label","kind":"String"},{"word":"max","kind":"Float"},{"word":"min","kind":"Float"},{"word":"name","kind":"String"},{"word":"related_space","kind":"Int"},{"word":"space_id","kind":"Int"},{"word":"stream","kind":"Set(B)","subblock":[{"word":"color","kind":"String"},{"word":"composite","kind":"String"},{"word":"group_function","kind":"String"},{"word":"max","kind":"Float"},{"word":"metric","kind":"String"},{"word":"min","kind":"Float"},{"word":"name","kind":"String"},{"word":"period","kind":"Int"},{"word":"source","kind":"String"},{"word":"summary_function","kind":"String"},{"word":"transform_function","kind":"String"},{"word":"units_long","kind":"String"},{"word":"units_short","kind":"String"},{"word":"id","kind":"String"}]},{"word":"type","kind":"String"},{"word":"id","kind":"String"}]}},"datas":{},"unknowns":{}}