{"registry_image":{"provider":"docker","arguments":[{"word":"name"}],"attributes":[{"word":"sha256_digest"}]},"container":{"provider":"docker","arguments":[{"word":"name"},{"word":"image"},{"word":"command"},{"word":"entrypoint"},{"word":"user"},{"word":"dns"},{"word":"dns_opts"},{"word":"dns_search"},{"word":"env"},{"word":"labels"},{"word":"links"},{"word":"hostname"},{"word":"domainname"},{"word":"restart"},{"word":"max_retry_count"},{"word":"must_run"},{"word":"capabilities"},{"word":"ports"},{"word":"host"},{"word":"privileged"},{"word":"publish_all_ports"},{"word":"volumes"},{"word":"memory"},{"word":"memory_swap"},{"word":"cpu_shares"},{"word":"log_driver"},{"word":"log_opts"},{"word":"network_mode"},{"word":"networks"},{"word":"destroy_grace_seconds"},{"word":"upload"}],"attributes":[{"word":"ip_address"},{"word":"ip_prefix_length"},{"word":"gateway"},{"word":"bridge"}]},"image":{"provider":"docker","arguments":[{"word":"name"},{"word":"keep_locally"},{"word":"pull_triggers"},{"word":"pull_trigger"}],"attributes":[{"word":"latest"}]},"network":{"provider":"docker","arguments":[{"word":"name"},{"word":"check_duplicate"},{"word":"driver"},{"word":"options"},{"word":"internal"},{"word":"ipam_driver"},{"word":"ipam_config"}],"attributes":[{"word":"id"},{"word":"scope"}]},"volume":{"provider":"docker","arguments":[{"word":"name"},{"word":"driver"},{"word":"driver_opts"}],"attributes":[{"word":"mountpoint"}]}}