{"virtual_machine":{"provider":"vsphere","arguments":[{"word":"name"},{"word":"vcpu"},{"word":"memory"},{"word":"memory_reservation"},{"word":"datacenter"},{"word":"cluster"},{"word":"resource_pool"},{"word":"gateway"},{"word":"domain"},{"word":"time_zone"},{"word":"dns_suffixes"},{"word":"dns_servers"},{"word":"network_interface"},{"word":"disk"},{"word":"detach_unknown_disks_on_delete"},{"word":"cdrom"},{"word":"windows_opt_config"},{"word":"linked_clone"},{"word":"enable_disk_uuid"},{"word":"custom_configuration_parameters"},{"word":"skip_customization"}],"attributes":[{"word":"id"},{"word":"uuid"},{"word":"name"},{"word":"vcpu"},{"word":"memory"},{"word":"datacenter"},{"word":"network_interface"},{"word":"network_interface"},{"word":"network_interface"},{"word":"network_interface"},{"word":"network_interface"}]},"folder":{"provider":"vsphere","arguments":[{"word":"path"},{"word":"datacenter"},{"word":"existing_path"}],"attributes":[]},"file":{"provider":"vsphere","arguments":[{"word":"source_file"},{"word":"destination_file"},{"word":"source_datacenter"},{"word":"datacenter"},{"word":"source_datastore"},{"word":"datastore"},{"word":"create_directories"}],"attributes":[]},"virtual_disk":{"provider":"vsphere","arguments":[{"word":"size"},{"word":"vmdk_path"},{"word":"type"},{"word":"adapter_type"},{"word":"datacenter"},{"word":"datastore"}],"attributes":[]}}